MANIFEST.in
README.txt
setup.py
d9t/__init__.py
d9t.json.egg-info/PKG-INFO
d9t.json.egg-info/SOURCES.txt
d9t.json.egg-info/dependency_links.txt
d9t.json.egg-info/entry_points.txt
d9t.json.egg-info/namespace_packages.txt
d9t.json.egg-info/paster_plugins.txt
d9t.json.egg-info/requires.txt
d9t.json.egg-info/top_level.txt
d9t.json.egg-info/zip-safe
d9t/json/README.txt
d9t/json/__init__.py
d9t/json/parser.py
d9t/json/tests.py
docs/AUTHOR.txt
docs/HISTORY.txt
docs/INSTALL.txt
docs/LICENSE.txt