Metadata-Version: 1.0
Name: d9t.json
Version: 0.4
Summary: A json parser
Home-page: http://d9t.de/os
Author: D9T GmbH, Daniel Kraft
Author-email: dk@d9t.de
License: GPLv3
Keywords: json d9t
Platform: UNKNOWN
Classifier: Programming Language :: Python
Classifier: Topic :: Software Development :: Libraries :: Python Modules
